CHANGES.txt
README.rst
README.txt
setup.py
src/gs_export/__init__.py
src/gs_export.egg-info/PKG-INFO
src/gs_export.egg-info/SOURCES.txt
src/gs_export.egg-info/dependency_links.txt
src/gs_export.egg-info/entry_points.txt
src/gs_export.egg-info/not-zip-safe
src/gs_export.egg-info/requires.txt
src/gs_export.egg-info/top_level.txt